binance_sdk_derivatives_trading_portfolio_margin/__init__.py
binance_sdk_derivatives_trading_portfolio_margin/derivatives_trading_portfolio_margin.py
binance_sdk_derivatives_trading_portfolio_margin/metadata.py
binance_sdk_derivatives_trading_portfolio_margin/rest_api/__init__.py
binance_sdk_derivatives_trading_portfolio_margin/rest_api/api/__init__.py
binance_sdk_derivatives_trading_portfolio_margin/rest_api/api/account_api.py
binance_sdk_derivatives_trading_portfolio_margin/rest_api/api/market_data_api.py
binance_sdk_derivatives_trading_portfolio_margin/rest_api/api/trade_api.py
binance_sdk_derivatives_trading_portfolio_margin/rest_api/api/user_data_streams_api.py
binance_sdk_derivatives_trading_portfolio_margin/rest_api/models/__init__.py
binance_sdk_derivatives_trading_portfolio_margin/rest_api/models/account_balance_response.py
binance_sdk_derivatives_trading_portfolio_margin/rest_api/models/account_balance_response1.py
binance_sdk_derivatives_trading_portfolio_margin/rest_api/models/account_balance_response1_inner.py
binance_sdk_derivatives_trading_portfolio_margin/rest_api/models/account_balance_response2.py
binance_sdk_derivatives_trading_portfolio_margin/rest_api/models/account_information_response.py
binance_sdk_derivatives_trading_portfolio_margin/rest_api/models/bnb_transfer_response.py
binance_sdk_derivatives_trading_portfolio_margin/rest_api/models/cancel_all_cm_open_conditional_orders_response.py
binance_sdk_derivatives_trading_portfolio_margin/rest_api/models/cancel_all_cm_open_orders_response.py
binance_sdk_derivatives_trading_portfolio_margin/rest_api/models/cancel_all_um_open_conditional_orders_response.py
binance_sdk_derivatives_trading_portfolio_margin/rest_api/models/cancel_all_um_open_orders_response.py
binance_sdk_derivatives_trading_portfolio_margin/rest_api/models/cancel_cm_conditional_order_response.py
binance_sdk_derivatives_trading_portfolio_margin/rest_api/models/cancel_cm_order_response.py
binance_sdk_derivatives_trading_portfolio_margin-4.0.0.dist-info/METADATA
binance_sdk_derivatives_trading_portfolio_margin-4.0.0.dist-info/WHEEL
binance_sdk_derivatives_trading_portfolio_margin-4.0.0.dist-info/licenses/LICENCE
binance_sdk_derivatives_trading_portfolio_margin-4.0.0.dist-info/RECORD
